setup.py
payment_slip/__init__.py
payment_slip/esr.py
python_paymentslip.egg-info/PKG-INFO
python_paymentslip.egg-info/SOURCES.txt
python_paymentslip.egg-info/dependency_links.txt
python_paymentslip.egg-info/not-zip-safe
python_paymentslip.egg-info/top_level.txt