Metadata-Version: 1.0
Name: python-paymentslip
Version: 0.1.0
Summary: Function for generating ESR-numbers for orange swiss payment slips (so called "Oranger Einzahlungsschein").
Home-page: http://github.com/philippeowagner/python-payment-slip
Author: Philippe O. Wagner
Author-email: wagner@arteria.ch
License: BSD
Platform: UNKNOWN
